{
    "Human_Bone_xenium_TENX": {
        "Healthy": [
            "TENX132"
        ]
    },
    "Human_Bowel_xenium_TENX": {
        "Cancer_COAD": [
            "TENX111",
            "TENX148"
        ],
        "Cancer_COADREAD": [
            "TENX139"
        ]
    },
    "Human_Breast_xenium_NCBI": {
        "Cancer_IDC": [
            "NCBI783",
            "NCBI784",
            "NCBI785"
        ]
    },
    "Human_Breast_xenium_TENX": {
        "Cancer_IDC": [
            "TENX97"
        ],
        "Cancer_ILC": [
            "TENX94",
            "TENX96"
        ]
    },
    "Human_Heart_xenium_TENX": {
        "Healthy": [
            "TENX119"
        ]
    },
    "Human_Kidney_xenium_TENX": {
        "Cancer_PRCC": [
            "TENX105"
        ],
        "Healthy": [
            "TENX106"
        ]
    },
    "Human_Liver_xenium_TENX": {
        "Cancer_HCC": [
            "TENX120"
        ],
        "Healthy": [
            "TENX121"
        ]
    },
    "Human_Lung_xenium_NCBI": {
        "Disease_CHP_Intermediate": [
            "NCBI864"
        ],
        "Disease_CTD_ILD_Intermediate": [
            "NCBI865"
        ],
        "Disease_ILD_Less_Fibrotic": [
            "NCBI881"
        ],
        "Disease_ILD_More_Fibrotic": [
            "NCBI882"
        ],
        "Disease_IPAF_Less_Fibrotic": [
            "NCBI860"
        ],
        "Disease_IPAF_More_Fibrotic": [
            "NCBI861"
        ],
        "Disease_IPF_Intermediate": [
            "NCBI867",
            "NCBI880"
        ],
        "Disease_IPF_Less_Fibrotic": [
            "NCBI858",
            "NCBI873"
        ],
        "Disease_IPF_More_Fibrotic": [
            "NCBI859",
            "NCBI866",
            "NCBI870"
        ],
        "Disease_Sarcoidosis_Less_Fibrotic": [
            "NCBI856"
        ],
        "Disease_Sarcoidosis_More_Fibrotic": [
            "NCBI857"
        ],
        "Healthy_Control": [
            "NCBI875",
            "NCBI876",
            "NCBI879",
            "NCBI883",
            "NCBI884"
        ]
    },
    "Human_Lung_xenium_TENX": {
        "Cancer_LUAD": [
            "TENX118",
            "TENX141"
        ]
    },
    "Human_Lymphoid_xenium_TENX": {
        "Cancer_ALL": [
            "TENX134"
        ],
        "Disease_Follicular_Lymphoid_Hyperplasia": [
            "TENX124"
        ],
        "Disease_Reactive_Follicular_Hyperplasia": [
            "TENX125"
        ],
        "Disease_Reactive_Lymph_Node": [
            "TENX143"
        ],
        "Healthy": [
            "TENX133"
        ]
    },
    "Human_Ovary_xenium_TENX": {
        "Cancer_HGSOC": [
            "TENX142"
        ]
    },
    "Human_Pancreas_xenium_TENX": {
        "Cancer_PAAD": [
            "TENX116",
            "TENX126",
            "TENX140"
        ]
    },
    "Human_Prostate_xenium_TENX": {
        "Cancer_PRAD": [
            "TENX157"
        ]
    },
    "Human_Skin_xenium_TENX": {
        "Cancer_SKCM": [
            "TENX115",
            "TENX117",
            "TENX158"
        ],
        "Healthy": [
            "TENX122",
            "TENX123"
        ]
    }
}